pingera_cli/__init__.py
pingera_cli/__main__.py
pingera_cli/main.py
pingera_cli/commands/__init__.py
pingera_cli/commands/auth.py
pingera_cli/commands/base.py
pingera_cli/commands/check_groups.py
pingera_cli/commands/check_secrets.py
pingera_cli/commands/checks.py
pingera_cli/commands/components.py
pingera_cli/commands/execution_groups.py
pingera_cli/commands/incidents.py
pingera_cli/commands/on_demand_checks.py
pingera_cli/commands/pages.py
pingera_cli/commands/secrets.py
pingera_cli/formatters/__init__.py
pingera_cli/formatters/base_formatter.py
pingera_cli/formatters/dns_formatter.py
pingera_cli/formatters/generic_formatter.py
pingera_cli/formatters/icmp_formatter.py
pingera_cli/formatters/multistep_formatter.py
pingera_cli/formatters/portscan_formatter.py
pingera_cli/formatters/registry.py
pingera_cli/formatters/ssl_formatter.py
pingera_cli/formatters/synthetic_formatter.py
pingera_cli/formatters/web_formatter.py
pingera_cli/utils/__init__.py
pingera_cli/utils/config.py
pingera_cli/utils/console.py
pingera_cli/utils/file_utils.py
pingera_cli-0.1.16.dist-info/licenses/LICENSE
pingera_cli-0.1.16.dist-info/METADATA
pingera_cli-0.1.16.dist-info/WHEEL
pingera_cli-0.1.16.dist-info/entry_points.txt
pingera_cli-0.1.16.dist-info/top_level.txt
pingera_cli-0.1.16.dist-info/RECORD
