Metadata-Version: 2.4
Name: pingera-cli
Version: 0.1.16
Summary: A beautiful Python CLI tool built with typer and rich, distributed via pip and based on Pingera SDK
Home-page: https://github.com/pingera/pingera-cli
Author: PingeraCLI Team
Author-email: Pingera Team <privet@pingera.ru>
Maintainer-email: Pingera Team <privet@pingera.ru>
License: MIT
Project-URL: Homepage, https://github.com/pingera/pingera-cli
Project-URL: Documentation, https://docs.pingera.com/cli
Project-URL: Repository, https://github.com/pingera/pingera-cli
Project-URL: Bug Tracker, https://github.com/pingera/pingera-cli/issues
Keywords: cli,pingera,network,monitoring,typer,rich,terminal
Classifier: Development Status :: 3 - Alpha
Classifier: Intended Audience :: Developers
Classifier: Intended Audience :: System Administrators
Classifier: License :: OSI Approved :: MIT License
Classifier: Operating System :: OS Independent
Classifier: Programming Language :: Python :: 3
Classifier: Programming Language :: Python :: 3.7
Classifier: Programming Language :: Python :: 3.8
Classifier: Programming Language :: Python :: 3.9
Classifier: Programming Language :: Python :: 3.10
Classifier: Programming Language :: Python :: 3.11
Classifier: Topic :: System :: Networking
Classifier: Topic :: Utilities
Classifier: Environment :: Console
Requires-Python: >=3.7
License-File: LICENSE
Requires-Dist: typer[all]>=0.9.0
Requires-Dist: rich>=13.0.0
Requires-Dist: pingera-sdk>=1.0.15
Requires-Dist: click>=8.0.0
Provides-Extra: dev
Requires-Dist: pytest>=6.0; extra == "dev"
Requires-Dist: pytest-cov; extra == "dev"
Requires-Dist: black; extra == "dev"
Requires-Dist: flake8; extra == "dev"
Requires-Dist: mypy; extra == "dev"
Dynamic: author
Dynamic: home-page
Dynamic: license-file
Dynamic: requires-python
